devpi_cleaner/__init__.py
devpi_cleaner/cli.py
devpi_cleaner/client.py
devpi_cleaner-0.3.0.dist-info/COPYING
devpi_cleaner-0.3.0.dist-info/METADATA
devpi_cleaner-0.3.0.dist-info/WHEEL
devpi_cleaner-0.3.0.dist-info/entry_points.txt
devpi_cleaner-0.3.0.dist-info/top_level.txt
devpi_cleaner-0.3.0.dist-info/RECORD
