Metadata-Version: 2.1
Name: devpi-cleaner
Version: 0.3.0
Summary: Enables batch removal of packages from a devpi server.
Home-page: https://github.com/blue-yonder/devpi-cleaner
Author: Matthias Bach
Author-email: matthias.bach@blue-yonder.com
License: new BSD
Platform: UNKNOWN
Classifier: Development Status :: 4 - Beta
Classifier: Environment :: Console
Classifier: Intended Audience :: Developers
Classifier: Intended Audience :: System Administrators
Classifier: License :: OSI Approved :: BSD License
Classifier: Natural Language :: English
Classifier: Operating System :: OS Independent
Classifier: Programming Language :: Python :: 3
Classifier: Programming Language :: Python :: 3.6
Classifier: Programming Language :: Python :: 3.7
Classifier: Programming Language :: Python :: 3.8
Classifier: Programming Language :: Python :: 3.9
Classifier: Topic :: System :: Archiving :: Packaging
Classifier: Programming Language :: Python :: Implementation :: CPython
Classifier: Programming Language :: Python :: Implementation :: PyPy
Classifier: Topic :: Utilities
Requires-Dist: devpi-client (>=2.4.0)
Requires-Dist: devpi-plumber (>=0.2.5)
Requires-Dist: setuptools (>=0.8)
Requires-Dist: six
Requires-Dist: progressbar2
